{"name":"Famous-views","tagline":"generate famo.us views","body":"Famous-views \r\n============\r\n\r\n[![Build Status](https://travis-ci.org/MFQ/famous-views.svg?branch=master)](https://travis-ci.org/MFQ/famous-views)\r\n\r\nGenerator boilerplate views of famo.us elegantly and quickly. \r\n\r\nInstallation\r\n------------\r\n\r\n    npm install -g famous-views\r\n\r\nCommands\r\n--------\r\n\r\n    famous-views main\r\n It will generate mainView.js file in your current directory\r\n\r\n    famous-views main -p lib/\r\nit will generate mainView.js to lib directory which was passed through **-p** parameter \r\n","google":"","note":"Don't delete this file! It's used internally to help with page regeneration."}